odoo/addons/account_invoice_production_lot/README.rst
odoo/addons/account_invoice_production_lot/__init__.py
odoo/addons/account_invoice_production_lot/__manifest__.py
odoo/addons/account_invoice_production_lot/demo/sale.xml
odoo/addons/account_invoice_production_lot/i18n/account_invoice_production_lot.pot
odoo/addons/account_invoice_production_lot/i18n/ar.po
odoo/addons/account_invoice_production_lot/i18n/bs.po
odoo/addons/account_invoice_production_lot/i18n/ca.po
odoo/addons/account_invoice_production_lot/i18n/cs.po
odoo/addons/account_invoice_production_lot/i18n/de.po
odoo/addons/account_invoice_production_lot/i18n/en_GB.po
odoo/addons/account_invoice_production_lot/i18n/es.po
odoo/addons/account_invoice_production_lot/i18n/es_CR.po
odoo/addons/account_invoice_production_lot/i18n/es_EC.po
odoo/addons/account_invoice_production_lot/i18n/es_MX.po
odoo/addons/account_invoice_production_lot/i18n/et.po
odoo/addons/account_invoice_production_lot/i18n/fr.po
odoo/addons/account_invoice_production_lot/i18n/fr_CH.po
odoo/addons/account_invoice_production_lot/i18n/hr.po
odoo/addons/account_invoice_production_lot/i18n/hr_HR.po
odoo/addons/account_invoice_production_lot/i18n/hu.po
odoo/addons/account_invoice_production_lot/i18n/it.po
odoo/addons/account_invoice_production_lot/i18n/ja.po
odoo/addons/account_invoice_production_lot/i18n/lt.po
odoo/addons/account_invoice_production_lot/i18n/mk.po
odoo/addons/account_invoice_production_lot/i18n/mn.po
odoo/addons/account_invoice_production_lot/i18n/nb.po
odoo/addons/account_invoice_production_lot/i18n/nl.po
odoo/addons/account_invoice_production_lot/i18n/nl_BE.po
odoo/addons/account_invoice_production_lot/i18n/nl_NL.po
odoo/addons/account_invoice_production_lot/i18n/pt.po
odoo/addons/account_invoice_production_lot/i18n/pt_BR.po
odoo/addons/account_invoice_production_lot/i18n/pt_PT.po
odoo/addons/account_invoice_production_lot/i18n/ro.po
odoo/addons/account_invoice_production_lot/i18n/ru.po
odoo_addon_account_invoice_production_lot-18.0.1.0.0.6.dist-info/METADATA
odoo_addon_account_invoice_production_lot-18.0.1.0.0.6.dist-info/WHEEL
odoo_addon_account_invoice_production_lot-18.0.1.0.0.6.dist-info/top_level.txt
odoo_addon_account_invoice_production_lot-18.0.1.0.0.6.dist-info/RECORD
