Metadata-Version: 2.1
Name: odoo-addon-account_invoice_production_lot
Version: 18.0.1.0.0.6
Requires-Python: >=3.10
Requires-Dist: odoo-addon-stock_picking_invoice_link==18.0.*
Requires-Dist: odoo==18.0.*
Summary: Display delivered serial numbers in invoice
Home-page: https://github.com/OCA/account-invoice-reporting
License: AGPL-3
Author: Agile Business Group,Tecnativa,Odoo Community Association (OCA)
Author-email: support@odoo-community.org
Classifier: Programming Language :: Python
Classifier: Framework :: Odoo
Classifier: Framework :: Odoo :: 18.0
Classifier: License :: OSI Approved :: GNU Affero General Public License v3
